txriakidx
