Metadata-Version: 1.0
Name: txRiakIdx
Version: 0.5.1
Summary: Twisted Riak client w/ transparent secondary indexes.
Home-page: https://github.com/williamsjj/txriakidx
Author: Jason Williams
Author-email: jasonjwwilliams@gmail.com
License: Apache 2.0
Download-URL: https://github.com/williamsjj/txriakidx/zipball/v0.5.1
Keywords: twisted,riak,txriak,indexes
Platform: UNKNOWN
